twinbooster/__init__.py
twinbooster/datasets/__init__.py
twinbooster/datasets/fsmol.py
twinbooster/notebooks/__init__.py
twinbooster/notebooks/eval_assay.py
twinbooster/notebooks/eval_zero_shot_lgbm_mf.py
twinbooster/notebooks/ablations/__init__.py
twinbooster/notebooks/ablations/eval_zero_shot_lgbm_mf.py
twinbooster/scripts/__init__.py
twinbooster/scripts/downloader.py
twinbooster/scripts/model.py
twinbooster/scripts/barlow_twins/__init__.py
twinbooster/scripts/barlow_twins/barlow_twins.py
twinbooster/scripts/barlow_twins/base_model.py
twinbooster/scripts/barlow_twins/hp_tuning.py
twinbooster/scripts/barlow_twins/preprocessor.py
twinbooster/scripts/barlow_twins/pretraining_pipeline.py
twinbooster/scripts/llm/__init__.py
twinbooster/scripts/llm/aid_embedding.py
twinbooster/scripts/llm/augmented_text_processor.py
twinbooster/scripts/llm/test_text_embedding.py
twinbooster/scripts/llm/text_embeddings.py
twinbooster/scripts/utils/__init__.py
twinbooster/scripts/utils/utils.py
twinbooster/scripts/utils/utils_chem.py
twinbooster/scripts/utils/utils_parallel.py
twinbooster-0.3.1.dist-info/LICENSE
twinbooster-0.3.1.dist-info/METADATA
twinbooster-0.3.1.dist-info/WHEEL
twinbooster-0.3.1.dist-info/top_level.txt
twinbooster-0.3.1.dist-info/RECORD
