Metadata-Version: 2.1
Name: twinbooster
Version: 0.3.1
Summary: Python package for TwinBooster: Synergising Chemical Structures and Bioassay Descriptions for Enhanced Molecular Property Prediction in Drug Discovery
Author-email: "Maximilian G. Schuh" <m.schuh@tum.de>
License: MIT License
Project-URL: Repository, https://github.com/maxischuh/TwinBooster
Requires-Python: ==3.8.*
License-File: LICENSE
Requires-Dist: numpy
Requires-Dist: pandas
Requires-Dist: torch ==2.0.1
Requires-Dist: transformers ==4.30.2
Requires-Dist: datasets
Requires-Dist: tqdm
Requires-Dist: scikit-learn
Requires-Dist: scipy
Requires-Dist: joblib
Requires-Dist: matplotlib
Requires-Dist: lightgbm ==3.3.5
Requires-Dist: rdkit ==2023.3.2
Requires-Dist: pynvml
Requires-Dist: ConfigSpace
Requires-Dist: smac
Requires-Dist: optuna
Requires-Dist: jupyterlab
Requires-Dist: pathlib
